csle_common/__init__.py
csle_common/__version__.py
csle_common/constants/__init__.py
csle_common/constants/constants.py
csle_common/consumer_threads/__init__.py
csle_common/consumer_threads/aggregated_host_metrics_thread.py
csle_common/consumer_threads/aggregated_ossec_ids_log_consumer_thread.py
csle_common/consumer_threads/aggregated_snort_ids_log_consumer_thread.py
csle_common/consumer_threads/aggregated_snort_ids_rule_log_consumer_thread.py
csle_common/consumer_threads/attacker_actions_consumer_thread.py
csle_common/consumer_threads/avg_host_metrics_thread.py
csle_common/consumer_threads/client_population_consumer_thread.py
csle_common/consumer_threads/defender_actions_consumer_thread.py
csle_common/consumer_threads/docker_host_stats_consumer_thread.py
csle_common/consumer_threads/docker_stats_consumer_thread.py
csle_common/consumer_threads/host_metrics_consumer_thread.py
csle_common/consumer_threads/ossec_ids_log_consumer_thread.py
csle_common/consumer_threads/snort_ids_log_consumer_thread.py
csle_common/controllers/__init__.py
csle_common/controllers/container_controller.py
csle_common/controllers/elk_controller.py
csle_common/controllers/emulation_env_controller.py
csle_common/controllers/five_g_core_controller.py
csle_common/controllers/five_g_cu_controller.py
csle_common/controllers/five_g_du_controller.py
csle_common/controllers/flags_controller.py
csle_common/controllers/host_controller.py
csle_common/controllers/installation_controller.py
csle_common/controllers/kafka_controller.py
csle_common/controllers/management_system_controller.py
csle_common/controllers/ossec_ids_controller.py
csle_common/controllers/ovs_controller.py
csle_common/controllers/resource_constraints_controller.py
csle_common/controllers/sdn_controller_manager.py
csle_common/controllers/simulation_env_controller.py
csle_common/controllers/snort_ids_controller.py
csle_common/controllers/topology_controller.py
csle_common/controllers/traffic_controller.py
csle_common-0.9.45.dist-info/METADATA
csle_common-0.9.45.dist-info/WHEEL
csle_common-0.9.45.dist-info/top_level.txt
csle_common-0.9.45.dist-info/RECORD
